{
  "objective": "BIOMASS_Ecoli_core_w_GAM",
  "reactions_ex": {
    "index": [
      "EX_ac_e",
      "EX_acald_e",
      "EX_akg_e",
      "EX_co2_e",
      "EX_etoh_e",
      "EX_for_e",
      "EX_fru_e",
      "EX_fum_e",
      "EX_glc__D_e",
      "EX_gln__L_e",
      "EX_glu__L_e",
      "EX_h_e",
      "EX_h2o_e",
      "EX_lac__D_e",
      "EX_mal__L_e",
      "EX_nh4_e",
      "EX_o2_e",
      "EX_pi_e",
      "EX_pyr_e",
      "EX_succ_e"
    ],
    "name": [
      "Acetate exchange",
      "Acetaldehyde exchange",
      "2-Oxoglutarate exchange",
      "CO2 exchange",
      "Ethanol exchange",
      "Formate exchange",
      "D-Fructose exchange",
      "Fumarate exchange",
      "D-Glucose exchange",
      "L-Glutamine exchange",
      "L-Glutamate exchange",
      "H+ exchange",
      "H2O exchange",
      "D-lactate exchange",
      "L-Malate exchange",
      "Ammonia exchange",
      "O2 exchange",
      "Phosphate exchange",
      "Pyruvate exchange",
      "Succinate exchange"
    ],
    "lb": [
      0.0,
      0.0,
      0.0,
      -1000.0,
      0.0,
      0.0,
      0.0,
      0.0,
      -10.0,
      0.0,
      0.0,
      -1000.0,
      -1000.0,
      0.0,
      0.0,
      -1000.0,
      -1000.0,
      -1000.0,
      0.0,
      0.0
    ],
    "ub": [
      1000.0,
      1000.0,
      1000.0,
      1000.0,
      1000.0,
      1000.0,
      1000.0,
      1000.0,
      1000.0,
      1000.0,
      1000.0,
      1000.0,
      1000.0,
      1000.0,
      1000.0,
      1000.0,
      1000.0,
      1000.0,
      1000.0,
      1000.0
    ]
  },
  "reactions_all": {
    "index": [
      "ACALD",
      "ACALDt",
      "ACKr",
      "ACONTa",
      "ACONTb",
      "ACt2r",
      "ADK1",
      "AKGDH",
      "AKGt2r",
      "ALCD2x",
      "ATPM",
      "ATPS4r",
      "BIOMASS_Ecoli_core_w_GAM",
      "CO2t",
      "CS",
      "CYTBD",
      "D_LACt2",
      "ENO",
      "ETOHt2r",
      "EX_ac_e",
      "EX_acald_e",
      "EX_akg_e",
      "EX_co2_e",
      "EX_etoh_e",
      "EX_for_e",
      "EX_fru_e",
      "EX_fum_e",
      "EX_glc__D_e",
      "EX_gln__L_e",
      "EX_glu__L_e",
      "EX_h_e",
      "EX_h2o_e",
      "EX_lac__D_e",
      "EX_mal__L_e",
      "EX_nh4_e",
      "EX_o2_e",
      "EX_pi_e",
      "EX_pyr_e",
      "EX_succ_e",
      "FBA",
      "FBP",
      "FORt2",
      "FORt",
      "FRD7",
      "FRUpts2",
      "FUM",
      "FUMt2_2",
      "G6PDH2r",
      "GAPD",
      "GLCpts",
      "GLNS",
      "GLNabc",
      "GLUDy",
      "GLUN",
      "GLUSy",
      "GLUt2r",
      "GND",
      "H2Ot",
      "ICDHyr",
      "ICL",
      "LDH_D",
      "MALS",
      "MALt2_2",
      "MDH",
      "ME1",
      "ME2",
      "NADH16",
      "NADTRHD",
      "NH4t",
      "O2t",
      "PDH",
      "PFK",
      "PFL",
      "PGI",
      "PGK",
      "PGL",
      "PGM",
      "PIt2r",
      "PPC",
      "PPCK",
      "PPS",
      "PTAr",
      "PYK",
      "PYRt2",
      "RPE",
      "RPI",
      "SUCCt2_2",
      "SUCCt3",
      "SUCDi",
      "SUCOAS",
      "TALA",
      "THD2",
      "TKT1",
      "TKT2",
      "TPI"
    ]
  },
  "genes": [
    "b1241",
    "b0351",
    "s0001",
    "b2296",
    "b1849",
    "b3115",
    "b0118",
    "b1276",
    "b0474",
    "b0726",
    "b0116",
    "b0727",
    "b2587",
    "b0356",
    "b1478",
    "b3736",
    "b3734",
    "b3732",
    "b3733",
    "b3739",
    "b3731",
    "b3737",
    "b3735",
    "b3738",
    "b0720",
    "b0733",
    "b0979",
    "b0978",
    "b0734",
    "b2975",
    "b3603",
    "b2779",
    "b1773",
    "b2097",
    "b2925",
    "b4232",
    "b3925",
    "b2492",
    "b0904",
    "b4153",
    "b4154",
    "b4152",
    "b4151",
    "b2415",
    "b1819",
    "b1818",
    "b1817",
    "b2416",
    "b1612",
    "b4122",
    "b1611",
    "b3528",
    "b1852",
    "b1779",
    "b2417",
    "b1621",
    "b1101",
    "b3870",
    "b1297",
    "b0809",
    "b0810",
    "b0811",
    "b1761",
    "b1524",
    "b0485",
    "b1812",
    "b3213",
    "b3212",
    "b4077",
    "b2029",
    "b0875",
    "b1136",
    "b4015",
    "b2133",
    "b1380",
    "b4014",
    "b2976",
    "b3236",
    "b1479",
    "b2463",
    "b2288",
    "b2283",
    "b2285",
    "b2278",
    "b2287",
    "b2280",
    "b2284",
    "b2282",
    "b2281",
    "b2277",
    "b2276",
    "b2286",
    "b2279",
    "b3962",
    "b1602",
    "b1603",
    "b0451",
    "b0114",
    "b0115",
    "b3916",
    "b1723",
    "b3951",
    "b3952",
    "b0902",
    "b3114",
    "b0903",
    "b2579",
    "b4025",
    "b2926",
    "b0767",
    "b4395",
    "b0755",
    "b3612",
    "b2987",
    "b3493",
    "b3956",
    "b3403",
    "b1702",
    "b2458",
    "b2297",
    "b1854",
    "b1676",
    "b3386",
    "b4301",
    "b4090",
    "b2914",
    "b0723",
    "b0724",
    "b0722",
    "b0721",
    "b0728",
    "b0729",
    "b2464",
    "b0008",
    "b2935",
    "b2465",
    "b3919"
  ]
}